httpx_kerberos/__init__.py
httpx_kerberos/__version__.py
httpx_kerberos/exceptions.py
httpx_kerberos/kerberos.py
httpx_kerberos-0.1.2.dist-info/METADATA
httpx_kerberos-0.1.2.dist-info/WHEEL
httpx_kerberos-0.1.2.dist-info/licenses/LICENSE
httpx_kerberos-0.1.2.dist-info/RECORD
