Metadata-Version: 2.4
Name: httpx_kerberos
Version: 0.1.2
Summary: Kerberos authentication for HTTPX
Project-URL: Homepage, https://github.com/raid-newvicx/httpx_kerberos
Project-URL: Source, https://github.com/raid-newvicx/httpx_kerberos
Author-email: Chris Newville <christopher.newville@raid.dev>
License-Expression: MIT
License-File: LICENSE
Classifier: Development Status :: 4 - Beta
Classifier: Intended Audience :: Developers
Classifier: License :: OSI Approved :: MIT License
Classifier: Operating System :: OS Independent
Classifier: Programming Language :: Python :: 3
Classifier: Programming Language :: Python :: 3 :: Only
Classifier: Programming Language :: Python :: 3.8
Classifier: Programming Language :: Python :: 3.9
Classifier: Programming Language :: Python :: 3.10
Classifier: Programming Language :: Python :: 3.11
Classifier: Programming Language :: Python :: 3.12
Requires-Python: <4.0,>=3.8
Requires-Dist: cryptography>=42.0.0
Requires-Dist: httpx<1.0.0,>=0.25.0
Requires-Dist: pyspnego>=0.10.2; sys_platform == 'win32'
Requires-Dist: pyspnego[kerberos]>=0.10.2; sys_platform != 'win32'
